MANIFEST.in
README.md
setup.cfg
setup.py
maltego/entities.mtz
src/sploitego/__init__.py
src/sploitego/resource.py
src/sploitego.egg-info/PKG-INFO
src/sploitego.egg-info/SOURCES.txt
src/sploitego.egg-info/dependency_links.txt
src/sploitego.egg-info/not-zip-safe
src/sploitego.egg-info/requires.txt
src/sploitego.egg-info/top_level.txt
src/sploitego/cmdtools/__init__.py
src/sploitego/cmdtools/amap.py
src/sploitego/cmdtools/nmap.py
src/sploitego/cmdtools/p0f.py
src/sploitego/resources/__init__.py
src/sploitego/resources/etc/__init__.py
src/sploitego/resources/etc/sploitego.conf
src/sploitego/resources/images/__init__.py
src/sploitego/resources/images/flags/__init__.py
src/sploitego/resources/images/flags/ad.png
src/sploitego/resources/images/flags/ae.png
src/sploitego/resources/images/flags/af.png
src/sploitego/resources/images/flags/ag.png
src/sploitego/resources/images/flags/ai.png
src/sploitego/resources/images/flags/al.png
src/sploitego/resources/images/flags/am.png
src/sploitego/resources/images/flags/an.png
src/sploitego/resources/images/flags/ao.png
src/sploitego/resources/images/flags/aq.png
src/sploitego/resources/images/flags/ar.png
src/sploitego/resources/images/flags/as.png
src/sploitego/resources/images/flags/at.png
src/sploitego/resources/images/flags/au.png
src/sploitego/resources/images/flags/aw.png
src/sploitego/resources/images/flags/ax.png
src/sploitego/resources/images/flags/az.png
src/sploitego/resources/images/flags/ba.png
src/sploitego/resources/images/flags/bb.png
src/sploitego/resources/images/flags/bd.png
src/sploitego/resources/images/flags/be.png
src/sploitego/resources/images/flags/bf.png
src/sploitego/resources/images/flags/bg.png
src/sploitego/resources/images/flags/bh.png
src/sploitego/resources/images/flags/bi.png
src/sploitego/resources/images/flags/bj.png
src/sploitego/resources/images/flags/bl.png
src/sploitego/resources/images/flags/bm.png
src/sploitego/resources/images/flags/bn.png
src/sploitego/resources/images/flags/bo.png
src/sploitego/resources/images/flags/br.png
src/sploitego/resources/images/flags/bs.png
src/sploitego/resources/images/flags/bt.png
src/sploitego/resources/images/flags/bv.png
src/sploitego/resources/images/flags/bw.png
