Metadata-Version: 1.0
Name: sploitego
Version: 1.2.2
Summary: Penetration testing transforms for Maltego.
Home-page: UNKNOWN
Author: Nadeem Douba
Author-email: ndouba@gmail.com
License: GPL
Platform: UNKNOWN
